django_response/__init__.py
django_response/djresponse.py
django_response-1.1.1.dist-info/DESCRIPTION.rst
django_response-1.1.1.dist-info/METADATA
django_response-1.1.1.dist-info/RECORD
django_response-1.1.1.dist-info/WHEEL
django_response-1.1.1.dist-info/metadata.json
django_response-1.1.1.dist-info/top_level.txt
